xor_unit.v
// xor_unit.v
module xor_unit(
    input  wire [7:0] data_in,
    input  wire [7:0] keystream,
    output wire [7:0] data_out
);
    assign data_out = data_in ^ keystream; // xors the  data_in and the key stream and stores it in data_output
endmodule

keystream_lfsr.v
// keystream_lfsr.v
module keystream_lfsr(
    input  wire        clk,                         //define clk                                                    
    input  wire        reset,                       //define reset
    input  wire        load_key,                    //define the load key
    input  wire [7:0]  key,                         // define the key
    output reg  [7:0]  keystream                    // define the output register keystream
);
    wire feedback;
    assign feedback = keystream[7] ^ keystream[5] ^ keystream[4] ^ keystream[3];
 //assign feedback the xor of bit 7 ,5,4,3
 // next block should run only when there is a rising edge on the clock or reset goes from zero to one
    always @(posedge clk or posedge reset) begin
        if (reset) begin
            keystream <= 8'h01;                         // loads hexa decimal 01 into lfsr if reset is 1
        end else if (load_key) begin
            keystream <= (key == 8'h00) ? 8'h01 : key;  
            // if reset is not active but load_key is then load key into keystream but if all keys are 00 then we must replace with 01 to avoid lockup just as we did above
        end else begin
            keystream <= {keystream[6:0], feedback};
            // this is the normal lfsr if there is no reset and no load key
            // that is it shifts the register left and adds the feedback bit at rightmost bit(bit 0)
            // the feedback bit is a temp wire with value the xor of bit 7 5 4 3
        end
    end
endmodule

xor_cipher.v
// xor_cipher.v
module xor_cipher(
    input  wire        clk,
    input  wire        reset,
    input  wire        load_key,
    input  wire [7:0]  data_in,   // plaintext or ciphertext as lfsr decoding and encoding uses the same operation
    input  wire [7:0]  key,       // this is the keystream genereated key tht is used to encrypt  
    output wire [7:0]  data_out   // result after xor it could be cipher text or the plain text depending on data_in
);
    wire [7:0] ks;

    keystream_lfsr ks_gen (
        // calls the keystream generation function
        .clk(clk),
        .reset(reset),
        .load_key(load_key),
        .key(key),
        .keystream(ks)
    );

    xor_unit xu (
        // calls the xor_unit module which is used to actually xor the keystream and data_in
        .data_in(data_in),
        .keystream(ks),
        .data_out(data_out)
    );
endmodule

tb_xor_cipher.v
`timescale 1ns / 1ps

module tb_xor_cipher;
    reg clk;
    reg reset;
    reg load_key;
    reg [7:0] key;
    reg [7:0] plaintext;
    wire [7:0] ciphertext;
    wire [7:0] decrypted;

    // Encryption instance
    xor_cipher enc (
        .clk(clk),
        .reset(reset),
        .load_key(load_key),
        .data_in(plaintext),
        .key(key),
        .data_out(ciphertext)
    );

    // Decryption instance
    xor_cipher dec (
        .clk(clk),
        .reset(reset),
        .load_key(load_key),
        .data_in(ciphertext),
        .key(key),
        .data_out(decrypted)
    );

    // clock
    initial clk = 0;
    always #5 clk = ~clk;

    // A reusable test task
    task run_test;
        input [7:0] key_in;
        input [7:0] plaintext_in;
        begin
            reset = 1;
            load_key = 0;
            key = key_in;
            plaintext = 8'h00;
            #10;
            reset = 0;

            load_key = 1; #10;
            load_key = 0; #10;

            plaintext = plaintext_in;
            #10;
            $display("KEY=%h  PLAINTEXT=%h  -->  CIPHERTEXT=%h  DECRYPTED=%h",
                     key, plaintext, ciphertext, decrypted);
            #10;
        end
    endtask

    initial begin
        $dumpfile("sim/xor_cipher.vcd");
        $dumpvars(0, tb_xor_cipher);
        $display("\n--- XOR Cipher Simulation Started ---\n");

        // << TEST CASES BEGIN >>
        // --- Original test cases ---
        run_test(8'hB3, 8'hCA); // Test 1
        run_test(8'hAC, 8'h41); // Test 2
        run_test(8'h00, 8'hFF); // Test 3
        run_test(8'hB3, 8'h4F); // added from terminal
        // << TEST CASES END >>

        #20;
        $display("\n--- Simulation Finished ---\n");
        $finish;
    end
endmodule

xor_cipher.vcd
$date
	Mon Nov 10 13:09:58 2025
$end
$version
	Icarus Verilog
$end
$timescale
	1ps
$end
$scope module tb_xor_cipher $end
$var wire 8 ! decrypted [7:0] $end
$var wire 8 " ciphertext [7:0] $end
$var reg 1 # clk $end
$var reg 8 $ key [7:0] $end
$var reg 1 % load_key $end
$var reg 8 & plaintext [7:0] $end
$var reg 1 ' reset $end
$scope module dec $end
$var wire 1 # clk $end
$var wire 8 ( key [7:0] $end
$var wire 1 % load_key $end
$var wire 1 ' reset $end
$var wire 8 ) ks [7:0] $end
$var wire 8 * data_out [7:0] $end
$var wire 8 + data_in [7:0] $end
$scope module ks_gen $end
$var wire 1 # clk $end
$var wire 1 , feedback $end
$var wire 8 - key [7:0] $end
$var wire 1 % load_key $end
$var wire 1 ' reset $end
$var reg 8 . keystream [7:0] $end
$upscope $end
$scope module xu $end
$var wire 8 / data_out [7:0] $end
$var wire 8 0 keystream [7:0] $end
$var wire 8 1 data_in [7:0] $end
$upscope $end
$upscope $end
$scope module enc $end
$var wire 1 # clk $end
$var wire 8 2 data_in [7:0] $end
$var wire 8 3 key [7:0] $end
$var wire 1 % load_key $end
$var wire 1 ' reset $end
$var wire 8 4 ks [7:0] $end
$var wire 8 5 data_out [7:0] $end
$scope module ks_gen $end
$var wire 1 # clk $end
$var wire 1 6 feedback $end
$var wire 8 7 key [7:0] $end
$var wire 1 % load_key $end
$var wire 1 ' reset $end
$var reg 8 8 keystream [7:0] $end
$upscope $end
$scope module xu $end
$var wire 8 9 data_in [7:0] $end
$var wire 8 : data_out [7:0] $end
$var wire 8 ; keystream [7:0] $end
$upscope $end
$upscope $end
$scope task run_test $end
$var reg 8 < key_in [7:0] $end
$var reg 8 = plaintext_in [7:0] $end
$upscope $end
$upscope $end
$enddefinitions $end
$comment Show the parameter values. $end
$dumpall
$end
#0
$dumpvars
b11001010 =
b10110011 <
b1 ;
b1 :
b0 9
b1 8
b10110011 7
06
b1 5
b1 4
b10110011 3
b0 2
b1 1
b1 0
b0 /
b1 .
b10110011 -
0,
b1 +
b0 *
b1 )
b10110011 (
1'
b0 &
0%
b10110011 $
0#
b1 "
b0 !
$end
#5000
1#
#10000
0#
1%
0'
#15000
16
1,
b10110011 "
b10110011 +
b10110011 1
b10110011 5
b10110011 :
b0 !
b0 *
b0 /
b10110011 4
b10110011 8
b10110011 ;
b10110011 )
b10110011 .
b10110011 0
1#
#20000
0#
0%
#25000
1,
16
b1100111 "
b1100111 +
b1100111 1
b1100111 5
b1100111 :
b1100111 )
b1100111 .
b1100111 0
b1100111 4
b1100111 8
b1100111 ;
1#
#30000
b11001010 !
b11001010 *
b11001010 /
b10101101 "
b10101101 +
b10101101 1
b10101101 5
b10101101 :
0#
b11001010 &
b11001010 2
b11001010 9
#35000
06
0,
b101 "
b101 +
b101 1
b101 5
b101 :
b11001010 !
b11001010 *
b11001010 /
b11001111 4
b11001111 8
b11001111 ;
b11001111 )
b11001111 .
b11001111 0
1#
#40000
0#
#45000
1,
16
b1010100 "
b1010100 +
b1010100 1
b1010100 5
b1010100 :
b10011110 )
b10011110 .
b10011110 0
b10011110 4
b10011110 8
b10011110 ;
1#
#50000
06
0,
b1 4
b1 8
b1 ;
b1 )
b1 .
b1 0
b0 !
b0 *
b0 /
b1 "
b1 +
b1 1
b1 5
b1 :
0#
b0 &
b0 2
b0 9
b10101100 $
b10101100 (
b10101100 -
b10101100 3
b10101100 7
1'
b1000001 =
b10101100 <
#55000
1#
#60000
0#
1%
0'
#65000
16
1,
b10101100 "
b10101100 +
b10101100 1
b10101100 5
b10101100 :
b0 !
b0 *
b0 /
b10101100 4
b10101100 8
b10101100 ;
b10101100 )
b10101100 .
b10101100 0
1#
#70000
0#
0%
#75000
0,
06
b1011001 "
b1011001 +
b1011001 1
b1011001 5
b1011001 :
b1011001 )
b1011001 .
b1011001 0
b1011001 4
b1011001 8
b1011001 ;
1#
#80000
b1000001 !
b1000001 *
b1000001 /
b11000 "
b11000 +
b11000 1
b11000 5
b11000 :
0#
b1000001 &
b1000001 2
b1000001 9
#85000
16
1,
b11110011 "
b11110011 +
b11110011 1
b11110011 5
b11110011 :
b1000001 !
b1000001 *
b1000001 /
b10110010 4
b10110010 8
b10110010 ;
b10110010 )
b10110010 .
b10110010 0
1#
#90000
0#
#95000
1,
16
b100100 "
b100100 +
b100100 1
b100100 5
b100100 :
b1100101 )
b1100101 .
b1100101 0
b1100101 4
b1100101 8
b1100101 ;
1#
#100000
06
0,
b1 4
b1 8
b1 ;
b1 )
b1 .
b1 0
b0 !
b0 *
b0 /
b1 "
b1 +
b1 1
b1 5
b1 :
0#
b0 &
b0 2
b0 9
b0 $
b0 (
b0 -
b0 3
b0 7
1'
b11111111 =
b0 <
#105000
1#
#110000
0#
1%
0'
#115000
1#
#120000
0#
0%
#125000
b10 "
b10 +
b10 1
b10 5
b10 :
b10 )
b10 .
b10 0
b10 4
b10 8
b10 ;
1#
#130000
b11111111 !
b11111111 *
b11111111 /
b11111101 "
b11111101 +
b11111101 1
b11111101 5
b11111101 :
0#
b11111111 &
b11111111 2
b11111111 9
#135000
b11111011 "
b11111011 +
b11111011 1
b11111011 5
b11111011 :
b11111111 !
b11111111 *
b11111111 /
b100 4
b100 8
b100 ;
b100 )
b100 .
b100 0
1#
#140000
0#
#145000
1,
16
b11110111 "
b11110111 +
b11110111 1
b11110111 5
b11110111 :
b1000 )
b1000 .
b1000 0
b1000 4
b1000 8
b1000 ;
1#
#150000
06
0,
b1 4
b1 8
b1 ;
b1 )
b1 .
b1 0
b0 !
b0 *
b0 /
b1 "
b1 +
b1 1
b1 5
b1 :
0#
b0 &
b0 2
b0 9
b10110011 $
b10110011 (
b10110011 -
b10110011 3
b10110011 7
1'
b1001111 =
b10110011 <
#155000
1#
#160000
0#
1%
0'
#165000
16
1,
b10110011 "
b10110011 +
b10110011 1
b10110011 5
b10110011 :
b0 !
b0 *
b0 /
b10110011 4
b10110011 8
b10110011 ;
b10110011 )
b10110011 .
b10110011 0
1#
#170000
0#
0%
#175000
1,
16
b1100111 "
b1100111 +
b1100111 1
b1100111 5
b1100111 :
b1100111 )
b1100111 .
b1100111 0
b1100111 4
b1100111 8
b1100111 ;
1#
#180000
b1001111 !
b1001111 *
b1001111 /
b101000 "
b101000 +
b101000 1
b101000 5
b101000 :
0#
b1001111 &
b1001111 2
b1001111 9
#185000
06
0,
b10000000 "
b10000000 +
b10000000 1
b10000000 5
b10000000 :
b1001111 !
b1001111 *
b1001111 /
b11001111 4
b11001111 8
b11001111 ;
b11001111 )
b11001111 .
b11001111 0
1#
#190000
0#
#195000
1,
16
b11010001 "
b11010001 +
b11010001 1
b11010001 5
b11010001 :
b10011110 )
b10011110 .
b10011110 0
b10011110 4
b10011110 8
b10011110 ;
1#
#200000
0#
#205000
b1110010 "
b1110010 +
b1110010 1
b1110010 5
b1110010 :
b1001111 !
b1001111 *
b1001111 /
b111101 4
b111101 8
b111101 ;
b111101 )
b111101 .
b111101 0
1#
#210000
0#
#215000
b110100 "
b110100 +
b110100 1
b110100 5
b110100 :
b1111011 )
b1111011 .
b1111011 0
b1111011 4
b1111011 8
b1111011 ;
1#
